{
  "tags": [
    {
      "title": "Redis",
      "slug": "slug",
      "amountOfVideos": 113,
      "id": "9431"
    },
    {
      "title": "Angular",
      "slug": "slug",
      "amountOfVideos": 57,
      "id": "7526"
    },
    {
      "title": "React",
      "slug": "slug",
      "amountOfVideos": 85,
      "id": "5dc7"
    },
    {
      "title": "Svelte",
      "slug": "slug",
      "amountOfVideos": 142,
      "id": "4965"
    },
    {
      "title": "Ember",
      "slug": "slug",
      "amountOfVideos": 96,
      "id": "4e6d"
    },
    {
      "title": "Backbon",
      "slug": "slug",
      "amountOfVideos": 124,
      "id": "2563"
    },
    {
      "title": "Aurelia",
      "slug": "slug",
      "amountOfVideos": 69,
      "id": "b868"
    },
    {
      "title": "Meteor",
      "slug": "slug",
      "amountOfVideos": 114,
      "id": "e863"
    },
    {
      "title": "Mithril",
      "slug": "slug",
      "amountOfVideos": 160,
      "id": "4508"
    },
    {
      "title": "Polymer",
      "slug": "slug",
      "amountOfVideos": 31,
      "id": "abef"
    },
    {
      "title": "Ember",
      "slug": "slug",
      "amountOfVideos": 109,
      "id": "38f9"
    },
    {
      "title": "Vue",
      "slug": "slug",
      "amountOfVideos": 78,
      "id": "7d08"
    },
    {
      "title": "Angular",
      "slug": "slug",
      "amountOfVideos": 62,
      "id": "64e7"
    },
    {
      "title": "Svelte",
      "slug": "slug",
      "amountOfVideos": 135,
      "id": "efb9"
    },
    {
      "title": "React",
      "slug": "slug",
      "amountOfVideos": 92,
      "id": "4cc4"
    },
    {
      "title": "Backbon",
      "slug": "slug",
      "amountOfVideos": 116,
      "id": "df12"
    },
    {
      "title": "Aurelia",
      "slug": "slug",
      "amountOfVideos": 71,
      "id": "9bc0"
    },
    {
      "title": "Meteor",
      "slug": "slug",
      "amountOfVideos": 120,
      "id": "2d32"
    },
    {
      "title": "Mithril",
      "slug": "slug",
      "amountOfVideos": 166,
      "id": "cafe"
    },
    {
      "title": "Polymer",
      "slug": "slug",
      "amountOfVideos": 39,
      "id": "bf8f"
    },
    {
      "title": "Vue",
      "slug": "slug",
      "amountOfVideos": 113,
      "id": "ebe1"
    },
    {
      "title": "Angular",
      "slug": "slug",
      "amountOfVideos": 57,
      "id": "2059"
    },
    {
      "title": "React",
      "slug": "slug",
      "amountOfVideos": 85,
      "id": "4d27"
    },
    {
      "title": "Svelte",
      "slug": "slug",
      "amountOfVideos": 142,
      "id": "e9b7"
    },
    {
      "title": "Ember",
      "slug": "slug",
      "amountOfVideos": 96,
      "id": "56af"
    },
    {
      "title": "Backbon",
      "slug": "slug",
      "amountOfVideos": 124,
      "id": "c2ec"
    },
    {
      "title": "Aurelia",
      "slug": "slug",
      "amountOfVideos": 69,
      "id": "30df"
    },
    {
      "title": "Meteor",
      "slug": "slug",
      "amountOfVideos": 114,
      "id": "3b10"
    },
    {
      "title": "Mithril",
      "slug": "slug",
      "amountOfVideos": 160,
      "id": "cd5f"
    },
    {
      "title": "Polymer",
      "slug": "slug",
      "amountOfVideos": 31,
      "id": "2f48"
    },
    {
      "title": "Ember",
      "slug": "slug",
      "amountOfVideos": 109,
      "id": "ff6f"
    },
    {
      "title": "Vue",
      "slug": "slug",
      "amountOfVideos": 78,
      "id": "6e51"
    },
    {
      "title": "Angular",
      "slug": "slug",
      "amountOfVideos": 62,
      "id": "569c"
    },
    {
      "title": "Svelte",
      "slug": "slug",
      "amountOfVideos": 135,
      "id": "95ea"
    },
    {
      "title": "React",
      "slug": "slug",
      "amountOfVideos": 92,
      "id": "9e19"
    },
    {
      "title": "Backbon",
      "slug": "slug",
      "amountOfVideos": 116,
      "id": "da18"
    },
    {
      "title": "Aurelia",
      "slug": "slug",
      "amountOfVideos": 71,
      "id": "2651"
    },
    {
      "title": "Meteor",
      "slug": "slug",
      "amountOfVideos": 120,
      "id": "241b"
    },
    {
      "title": "Mithril",
      "slug": "slug",
      "amountOfVideos": 166,
      "id": "5edf"
    },
    {
      "title": "Polymer",
      "slug": "slug",
      "amountOfVideos": 39,
      "id": "dc31"
    },
    {
      "title": "Vue",
      "slug": "slug",
      "amountOfVideos": 113,
      "id": "f416"
    },
    {
      "title": "Angular",
      "slug": "slug",
      "amountOfVideos": 57,
      "id": "9410"
    },
    {
      "title": "React",
      "slug": "slug",
      "amountOfVideos": 85,
      "id": "1716"
    },
    {
      "title": "Svelte",
      "slug": "slug",
      "amountOfVideos": 142,
      "id": "9e1c"
    },
    {
      "title": "Ember",
      "slug": "slug",
      "amountOfVideos": 96,
      "id": "3854"
    },
    {
      "title": "Backbon",
      "slug": "slug",
      "amountOfVideos": 124,
      "id": "ac23"
    },
    {
      "title": "Aurelia",
      "slug": "slug",
      "amountOfVideos": 69,
      "id": "d6d7"
    },
    {
      "title": "Meteor",
      "slug": "slug",
      "amountOfVideos": 114,
      "id": "c316"
    },
    {
      "title": "Mithril",
      "slug": "slug",
      "amountOfVideos": 160,
      "id": "24c4"
    },
    {
      "title": "Polymer",
      "slug": "slug",
      "amountOfVideos": 31,
      "id": "f33b"
    },
    {
      "title": "Ember",
      "slug": "slug",
      "amountOfVideos": 109,
      "id": "c3fa"
    },
    {
      "title": "Vue",
      "slug": "slug",
      "amountOfVideos": 78,
      "id": "f1d8"
    },
    {
      "title": "Angular",
      "slug": "slug",
      "amountOfVideos": 62,
      "id": "6bc6"
    },
    {
      "title": "Svelte",
      "slug": "slug",
      "amountOfVideos": 135,
      "id": "18df"
    },
    {
      "title": "React",
      "slug": "slug",
      "amountOfVideos": 92,
      "id": "8549"
    },
    {
      "title": "Backbon",
      "slug": "slug",
      "amountOfVideos": 116,
      "id": "57c2"
    },
    {
      "title": "Aurelia",
      "slug": "slug",
      "amountOfVideos": 71,
      "id": "20e1"
    },
    {
      "title": "Meteor",
      "slug": "slug",
      "amountOfVideos": 120,
      "id": "89b8"
    },
    {
      "title": "Mithril",
      "slug": "slug",
      "amountOfVideos": 166,
      "id": "024a"
    },
    {
      "title": "Polymer",
      "slug": "slug",
      "amountOfVideos": 39,
      "id": "ebe8"
    },
    {
      "title": "Vue",
      "slug": "slug",
      "amountOfVideos": 113,
      "id": "1383"
    },
    {
      "title": "Angular",
      "slug": "slug",
      "amountOfVideos": 57,
      "id": "05bb"
    },
    {
      "title": "React",
      "slug": "slug",
      "amountOfVideos": 85,
      "id": "d27b"
    },
    {
      "title": "Svelte",
      "slug": "slug",
      "amountOfVideos": 142,
      "id": "c030"
    },
    {
      "title": "Ember",
      "slug": "slug",
      "amountOfVideos": 96,
      "id": "f574"
    },
    {
      "title": "Backbon",
      "slug": "slug",
      "amountOfVideos": 124,
      "id": "c530"
    },
    {
      "title": "Aurelia",
      "slug": "slug",
      "amountOfVideos": 69,
      "id": "e18f"
    },
    {
      "title": "Meteor",
      "slug": "slug",
      "amountOfVideos": 114,
      "id": "b58a"
    },
    {
      "title": "Mithril",
      "slug": "slug",
      "amountOfVideos": 160,
      "id": "e7af"
    },
    {
      "title": "Polymer",
      "slug": "slug",
      "amountOfVideos": 31,
      "id": "0a43"
    },
    {
      "title": "Ember",
      "slug": "slug",
      "amountOfVideos": 109,
      "id": "d242"
    },
    {
      "title": "Vue",
      "slug": "slug",
      "amountOfVideos": 78,
      "id": "d959"
    },
    {
      "title": "Angular",
      "slug": "slug",
      "amountOfVideos": 62,
      "id": "dcbb"
    },
    {
      "title": "Svelte",
      "slug": "slug",
      "amountOfVideos": 135,
      "id": "7286"
    },
    {
      "title": "React",
      "slug": "slug",
      "amountOfVideos": 92,
      "id": "dc08"
    },
    {
      "title": "Backbon",
      "slug": "slug",
      "amountOfVideos": 116,
      "id": "b53c"
    },
    {
      "title": "Aurelia",
      "slug": "slug",
      "amountOfVideos": 71,
      "id": "27db"
    },
    {
      "title": "Meteor",
      "slug": "slug",
      "amountOfVideos": 120,
      "id": "0098"
    },
    {
      "title": "Mithril",
      "slug": "slug",
      "amountOfVideos": 166,
      "id": "9137"
    },
    {
      "title": "Polymer",
      "slug": "slug",
      "amountOfVideos": 39,
      "id": "f2c3"
    },
    {
      "title": "Vue",
      "slug": "slug",
      "amountOfVideos": 113,
      "id": "7b86"
    },
    {
      "title": "Angular",
      "slug": "slug",
      "amountOfVideos": 57,
      "id": "0067"
    },
    {
      "title": "React",
      "slug": "slug",
      "amountOfVideos": 85,
      "id": "6a18"
    },
    {
      "title": "Svelte",
      "slug": "slug",
      "amountOfVideos": 142,
      "id": "06c3"
    },
    {
      "title": "Ember",
      "slug": "slug",
      "amountOfVideos": 96,
      "id": "930b"
    },
    {
      "title": "Backbon",
      "slug": "slug",
      "amountOfVideos": 124,
      "id": "d4ab"
    },
    {
      "title": "Aurelia",
      "slug": "slug",
      "amountOfVideos": 69,
      "id": "deba"
    },
    {
      "title": "Meteor",
      "slug": "slug",
      "amountOfVideos": 114,
      "id": "065e"
    },
    {
      "title": "Mithril",
      "slug": "slug",
      "amountOfVideos": 160,
      "id": "a342"
    },
    {
      "title": "Polymer",
      "slug": "slug",
      "amountOfVideos": 31,
      "id": "77c0"
    },
    {
      "title": "Ember",
      "slug": "slug",
      "amountOfVideos": 109,
      "id": "e314"
    },
    {
      "title": "Vue",
      "slug": "slug",
      "amountOfVideos": 78,
      "id": "2f85"
    },
    {
      "title": "Angular",
      "slug": "slug",
      "amountOfVideos": 62,
      "id": "403e"
    },
    {
      "title": "Svelte",
      "slug": "slug",
      "amountOfVideos": 135,
      "id": "a35c"
    },
    {
      "title": "React",
      "slug": "slug",
      "amountOfVideos": 92,
      "id": "0e8a"
    },
    {
      "title": "Backbon",
      "slug": "slug",
      "amountOfVideos": 116,
      "id": "62be"
    },
    {
      "title": "Aurelia",
      "slug": "slug",
      "amountOfVideos": 71,
      "id": "8051"
    },
    {
      "title": "Meteor",
      "slug": "slug",
      "amountOfVideos": 120,
      "id": "b835"
    },
    {
      "title": "Mithril",
      "slug": "slug",
      "amountOfVideos": 166,
      "id": "85c7"
    },
    {
      "title": "Polymer",
      "slug": "slug",
      "amountOfVideos": 39,
      "id": "0639"
    },
    {
      "title": "Vue",
      "slug": "slug",
      "amountOfVideos": 113,
      "id": "513d"
    },
    {
      "title": "Angular",
      "slug": "slug",
      "amountOfVideos": 57,
      "id": "fcfd"
    },
    {
      "title": "React",
      "slug": "slug",
      "amountOfVideos": 85,
      "id": "c345"
    },
    {
      "title": "Svelte",
      "slug": "slug",
      "amountOfVideos": 142,
      "id": "c1ba"
    },
    {
      "title": "Ember",
      "slug": "slug",
      "amountOfVideos": 96,
      "id": "ad98"
    },
    {
      "title": "Backbon",
      "slug": "slug",
      "amountOfVideos": 124,
      "id": "e844"
    },
    {
      "title": "Aurelia",
      "slug": "slug",
      "amountOfVideos": 69,
      "id": "f09c"
    },
    {
      "title": "Meteor",
      "slug": "slug",
      "amountOfVideos": 114,
      "id": "b7ee"
    },
    {
      "title": "Mithril",
      "slug": "slug",
      "amountOfVideos": 160,
      "id": "8c6d"
    },
    {
      "title": "Polymer",
      "slug": "slug",
      "amountOfVideos": 31,
      "id": "1b9c"
    },
    {
      "title": "Ember",
      "slug": "slug",
      "amountOfVideos": 109,
      "id": "26b4"
    },
    {
      "title": "Vue",
      "slug": "slug",
      "amountOfVideos": 78,
      "id": "5a3d"
    },
    {
      "title": "Angular",
      "slug": "slug",
      "amountOfVideos": 62,
      "id": "497d"
    },
    {
      "title": "Svelte",
      "slug": "slug",
      "amountOfVideos": 135,
      "id": "12bb"
    },
    {
      "title": "React",
      "slug": "slug",
      "amountOfVideos": 92,
      "id": "bda4"
    },
    {
      "title": "Backbon",
      "slug": "slug",
      "amountOfVideos": 116,
      "id": "7510"
    },
    {
      "title": "Aurelia",
      "slug": "slug",
      "amountOfVideos": 71,
      "id": "dd85"
    },
    {
      "title": "Meteor",
      "slug": "slug",
      "amountOfVideos": 120,
      "id": "7bd8"
    },
    {
      "title": "Mithril",
      "slug": "slug",
      "amountOfVideos": 166,
      "id": "20f9"
    },
    {
      "title": "Polymer",
      "slug": "slug",
      "amountOfVideos": 39,
      "id": "5148"
    },
    {
      "title": "Vue",
      "slug": "slug",
      "amountOfVideos": 113,
      "id": "ee67"
    },
    {
      "title": "Angular",
      "slug": "slug",
      "amountOfVideos": 57,
      "id": "e8cd"
    },
    {
      "title": "React",
      "slug": "slug",
      "amountOfVideos": 85,
      "id": "d01d"
    },
    {
      "title": "Svelte",
      "slug": "slug",
      "amountOfVideos": 142,
      "id": "c0fa"
    },
    {
      "title": "Ember",
      "slug": "slug",
      "amountOfVideos": 96,
      "id": "8740"
    },
    {
      "title": "Backbon",
      "slug": "slug",
      "amountOfVideos": 124,
      "id": "83e7"
    },
    {
      "title": "Aurelia",
      "slug": "slug",
      "amountOfVideos": 69,
      "id": "e10c"
    },
    {
      "title": "Meteor",
      "slug": "slug",
      "amountOfVideos": 114,
      "id": "d391"
    },
    {
      "title": "Mithril",
      "slug": "slug",
      "amountOfVideos": 160,
      "id": "dbf6"
    },
    {
      "title": "Polymer",
      "slug": "slug",
      "amountOfVideos": 31,
      "id": "b8b0"
    },
    {
      "title": "Ember",
      "slug": "slug",
      "amountOfVideos": 109,
      "id": "d8e4"
    },
    {
      "title": "Vue",
      "slug": "slug",
      "amountOfVideos": 78,
      "id": "1a9e"
    },
    {
      "title": "Angular",
      "slug": "slug",
      "amountOfVideos": 62,
      "id": "4e09"
    },
    {
      "title": "Svelte",
      "slug": "slug",
      "amountOfVideos": 135,
      "id": "230b"
    },
    {
      "title": "React",
      "slug": "slug",
      "amountOfVideos": 92,
      "id": "bc66"
    },
    {
      "title": "Backbon",
      "slug": "slug",
      "amountOfVideos": 116,
      "id": "c1f0"
    },
    {
      "title": "Aurelia",
      "slug": "slug",
      "amountOfVideos": 71,
      "id": "a0c2"
    },
    {
      "title": "Meteor",
      "slug": "slug",
      "amountOfVideos": 120,
      "id": "5831"
    },
    {
      "title": "Mithril",
      "slug": "slug",
      "amountOfVideos": 166,
      "id": "99ae"
    },
    {
      "title": "Polymer",
      "slug": "slug",
      "amountOfVideos": 39,
      "id": "ea28"
    },
    {
      "title": "Vue",
      "slug": "slug",
      "amountOfVideos": 113,
      "id": "c99d"
    },
    {
      "title": "Angular",
      "slug": "slug",
      "amountOfVideos": 57,
      "id": "df5e"
    },
    {
      "title": "React",
      "slug": "slug",
      "amountOfVideos": 85,
      "id": "db77"
    },
    {
      "title": "Svelte",
      "slug": "slug",
      "amountOfVideos": 142,
      "id": "53d5"
    },
    {
      "title": "Ember",
      "slug": "slug",
      "amountOfVideos": 96,
      "id": "f695"
    },
    {
      "title": "Backbon",
      "slug": "slug",
      "amountOfVideos": 124,
      "id": "bd3a"
    },
    {
      "title": "Aurelia",
      "slug": "slug",
      "amountOfVideos": 69,
      "id": "e40e"
    },
    {
      "title": "Meteor",
      "slug": "slug",
      "amountOfVideos": 114,
      "id": "7135"
    },
    {
      "title": "Mithril",
      "slug": "slug",
      "amountOfVideos": 160,
      "id": "a248"
    },
    {
      "title": "Polymer",
      "slug": "slug",
      "amountOfVideos": 31,
      "id": "b671"
    },
    {
      "title": "Ember",
      "slug": "slug",
      "amountOfVideos": 109,
      "id": "b99b"
    },
    {
      "title": "Vue",
      "slug": "slug",
      "amountOfVideos": 78,
      "id": "0226"
    },
    {
      "title": "Angular",
      "slug": "slug",
      "amountOfVideos": 62,
      "id": "2c07"
    },
    {
      "title": "Svelte",
      "slug": "slug",
      "amountOfVideos": 135,
      "id": "9e22"
    },
    {
      "title": "React",
      "slug": "slug",
      "amountOfVideos": 92,
      "id": "82a1"
    },
    {
      "title": "Backbon",
      "slug": "slug",
      "amountOfVideos": 116,
      "id": "5d02"
    },
    {
      "title": "Aurelia",
      "slug": "slug",
      "amountOfVideos": 71,
      "id": "e455"
    },
    {
      "title": "Meteor",
      "slug": "slug",
      "amountOfVideos": 120,
      "id": "8e85"
    },
    {
      "title": "Mithril",
      "slug": "slug",
      "amountOfVideos": 166,
      "id": "3782"
    },
    {
      "title": "Polymer",
      "slug": "slug",
      "amountOfVideos": 39,
      "id": "a224"
    },
    {
      "title": "Vue",
      "slug": "slug",
      "amountOfVideos": 113,
      "id": "a5ea"
    },
    {
      "title": "Angular",
      "slug": "slug",
      "amountOfVideos": 57,
      "id": "379b"
    },
    {
      "title": "React",
      "slug": "slug",
      "amountOfVideos": 85,
      "id": "2847"
    },
    {
      "title": "Svelte",
      "slug": "slug",
      "amountOfVideos": 142,
      "id": "b057"
    },
    {
      "title": "Ember",
      "slug": "slug",
      "amountOfVideos": 96,
      "id": "2f59"
    },
    {
      "title": "Backbon",
      "slug": "slug",
      "amountOfVideos": 124,
      "id": "da05"
    },
    {
      "title": "Aurelia",
      "slug": "slug",
      "amountOfVideos": 69,
      "id": "87a1"
    },
    {
      "title": "Meteor",
      "slug": "slug",
      "amountOfVideos": 114,
      "id": "0e44"
    },
    {
      "title": "Mithril",
      "slug": "slug",
      "amountOfVideos": 160,
      "id": "0c9f"
    },
    {
      "title": "Polymer",
      "slug": "slug",
      "amountOfVideos": 31,
      "id": "aab5"
    },
    {
      "title": "Ember",
      "slug": "slug",
      "amountOfVideos": 109,
      "id": "b967"
    },
    {
      "title": "Vue",
      "slug": "slug",
      "amountOfVideos": 78,
      "id": "031c"
    },
    {
      "title": "Angular",
      "slug": "slug",
      "amountOfVideos": 62,
      "id": "44b6"
    },
    {
      "title": "Svelte",
      "slug": "slug",
      "amountOfVideos": 135,
      "id": "496c"
    },
    {
      "title": "React",
      "slug": "slug",
      "amountOfVideos": 92,
      "id": "7ee4"
    },
    {
      "title": "Backbon",
      "slug": "slug",
      "amountOfVideos": 116,
      "id": "e371"
    },
    {
      "title": "Aurelia",
      "slug": "slug",
      "amountOfVideos": 71,
      "id": "373e"
    },
    {
      "title": "Meteor",
      "slug": "slug",
      "amountOfVideos": 120,
      "id": "aae3"
    },
    {
      "title": "Mithril",
      "slug": "slug",
      "amountOfVideos": 166,
      "id": "3718"
    },
    {
      "title": "Polymer",
      "slug": "slug",
      "amountOfVideos": 39,
      "id": "ae9b"
    },
    {
      "title": "Vue",
      "slug": "slug",
      "amountOfVideos": 113,
      "id": "b9b1"
    },
    {
      "title": "Angular",
      "slug": "slug",
      "amountOfVideos": 57,
      "id": "713d"
    },
    {
      "title": "React",
      "slug": "slug",
      "amountOfVideos": 85,
      "id": "2782"
    },
    {
      "title": "Svelte",
      "slug": "slug",
      "amountOfVideos": 142,
      "id": "aeaf"
    },
    {
      "title": "Ember",
      "slug": "slug",
      "amountOfVideos": 96,
      "id": "7507"
    },
    {
      "title": "Backbon",
      "slug": "slug",
      "amountOfVideos": 124,
      "id": "ba4f"
    },
    {
      "title": "Aurelia",
      "slug": "slug",
      "amountOfVideos": 69,
      "id": "1987"
    },
    {
      "title": "Meteor",
      "slug": "slug",
      "amountOfVideos": 114,
      "id": "3315"
    },
    {
      "title": "Mithril",
      "slug": "slug",
      "amountOfVideos": 160,
      "id": "c198"
    },
    {
      "title": "Polymer",
      "slug": "slug",
      "amountOfVideos": 31,
      "id": "0eba"
    },
    {
      "title": "Ember",
      "slug": "slug",
      "amountOfVideos": 109,
      "id": "6a23"
    },
    {
      "title": "Vue",
      "slug": "slug",
      "amountOfVideos": 78,
      "id": "246d"
    },
    {
      "title": "Angular",
      "slug": "slug",
      "amountOfVideos": 62,
      "id": "4af0"
    },
    {
      "title": "Svelte",
      "slug": "slug",
      "amountOfVideos": 135,
      "id": "024c"
    },
    {
      "title": "React",
      "slug": "slug",
      "amountOfVideos": 92,
      "id": "63b3"
    },
    {
      "title": "Backbon",
      "slug": "slug",
      "amountOfVideos": 116,
      "id": "ad45"
    },
    {
      "title": "Aurelia",
      "slug": "slug",
      "amountOfVideos": 71,
      "id": "860b"
    },
    {
      "title": "Meteor",
      "slug": "slug",
      "amountOfVideos": 120,
      "id": "802d"
    },
    {
      "title": "Mithril",
      "slug": "slug",
      "amountOfVideos": 166,
      "id": "a079"
    },
    {
      "title": "Polymer",
      "slug": "slug",
      "amountOfVideos": 39,
      "id": "c0c4"
    },
    {
      "id": "e915",
      "title": "Vue Stats ",
      "slug": "vue-stats-",
      "amountOfVideos": 0
    },
    {
      "id": "cd9c",
      "title": "React Components",
      "slug": "react-components",
      "amountOfVideos": 0
    },
    {
      "id": "44de",
      "title": "Svelt Primeira Aula",
      "slug": "svelt-primeira-aula",
      "amountOfVideos": 0
    },
    {
      "id": "a0a0",
      "title": "Testando com mutation",
      "slug": "testando-com-mutation",
      "amountOfVideos": 0
    },
    {
      "id": "0ad3",
      "title": "Testando Use Mutation Para Renderização",
      "slug": "testando-use-mutation-para-renderizacao",
      "amountOfVideos": 0
    }
  ]
}